{
  "0": [
    {
      "state_id": 1,
      "candidate": "ID . ID = Expr",
      "candidate_text": "GraphicsWindow.BackgroundColor = \"Black\""
    }
  ],
  "14": [
    {
      "state_id": 188,
      "candidate": ". ID = Expr",
      "candidate_text": ".BackgroundColor = \"Black\""
    }
  ],
  "15": [
    {
      "state_id": 259,
      "candidate": "ID = Expr",
      "candidate_text": "BackgroundColor = \"Black\""
    }
  ],
  "31": [
    {
      "state_id": 214,
      "candidate": "= Expr",
      "candidate_text": "= \"Black\""
    }
  ],
  "33": [
    {
      "state_id": 75,
      "candidate": "STR",
      "candidate_text": "\"Black\""
    }
  ],
  "42": [
    {
      "state_id": 97,
      "candidate": "ID . ID = Expr",
      "candidate_text": "GraphicsWindow.MouseDown = OnMouseDown"
    }
  ],
  "56": [
    {
      "state_id": 188,
      "candidate": ". ID = Expr",
      "candidate_text": ".MouseDown = OnMouseDown"
    }
  ],
  "57": [
    {
      "state_id": 259,
      "candidate": "ID = Expr",
      "candidate_text": "MouseDown = OnMouseDown"
    }
  ],
  "67": [
    {
      "state_id": 214,
      "candidate": "= Expr",
      "candidate_text": "= OnMouseDown"
    }
  ],
  "69": [
    {
      "state_id": 75,
      "candidate": "ID",
      "candidate_text": "OnMouseDown"
    }
  ],
  "82": [
    {
      "state_id": 97,
      "candidate": "Stmt_token7 ID CRStmtCRs Stmt_token8",
      "candidate_text": "Sub OnMouseDown     "
    }
  ],
  "86": [
    {
      "state_id": 244,
      "candidate": "ID CRStmtCRs Stmt_token8",
      "candidate_text": "OnMouseDown     "
    }
  ],
  "102": [
    {
      "state_id": 199,
      "candidate": "CR_token2",
      "candidate_text": ""
    }
  ],
  "104": [
    {
      "state_id": 105,
      "candidate": "ID = Expr",
      "candidate_text": "pic = Flickr.GetRandomPicture(\"mountains, river\")"
    }
  ],
  "108": [
    {
      "state_id": 184,
      "candidate": "= Expr",
      "candidate_text": "= Flickr.GetRandomPicture(\"mountains, river\")"
    }
  ],
  "110": [
    {
      "state_id": 70,
      "candidate": "ID . ID ( Exprs )",
      "candidate_text": "Flickr.GetRandomPicture(\"mountains, river\")"
    }
  ],
  "116": [
    {
      "state_id": 5,
      "candidate": ". ID ( Exprs )",
      "candidate_text": ".GetRandomPicture(\"mountains, river\")"
    }
  ],
  "117": [
    {
      "state_id": 260,
      "candidate": "ID ( Exprs )",
      "candidate_text": "GetRandomPicture(\"mountains, river\")"
    }
  ],
  "133": [
    {
      "state_id": 24,
      "candidate": "( Exprs )",
      "candidate_text": "(\"mountains, river\")"
    }
  ],
  "134": [
    {
      "state_id": 26,
      "candidate": "STR",
      "candidate_text": "\"mountains, river\""
    }
  ],
  "152": [
    {
      "state_id": 249,
      "candidate": ")",
      "candidate_text": ")"
    }
  ],
  "158": [
    {
      "state_id": 206,
      "candidate": "CR_token2",
      "candidate_text": ""
    }
  ],
  "160": [
    {
      "state_id": 106,
      "candidate": "ID . ID ( Exprs )",
      "candidate_text": "GraphicsWindow.DrawResizedImage(pic, 0, 0, 640, 480)"
    }
  ],
  "174": [
    {
      "state_id": 184,
      "candidate": ". ID ( Exprs )",
      "candidate_text": ".DrawResizedImage(pic, 0, 0, 640, 480)"
    }
  ],
  "175": [
    {
      "state_id": 255,
      "candidate": "ID ( Exprs )",
      "candidate_text": "DrawResizedImage(pic, 0, 0, 640, 480)"
    }
  ],
  "191": [
    {
      "state_id": 221,
      "candidate": "( Exprs )",
      "candidate_text": "(pic, 0, 0, 640, 480)"
    }
  ],
  "192": [
    {
      "state_id": 27,
      "candidate": "ID",
      "candidate_text": "pic"
    }
  ],
  "195": [
    {
      "state_id": 217,
      "candidate": ", MoreThanOneExpr",
      "candidate_text": ", 0, 0, 640, 480"
    }
  ],
  "197": [
    {
      "state_id": 54,
      "candidate": "NUM",
      "candidate_text": "0"
    }
  ],
  "198": [
    {
      "state_id": 217,
      "candidate": ", MoreThanOneExpr",
      "candidate_text": ", 0, 640, 480"
    }
  ],
  "200": [
    {
      "state_id": 54,
      "candidate": "NUM",
      "candidate_text": "0"
    }
  ],
  "201": [
    {
      "state_id": 217,
      "candidate": ", MoreThanOneExpr",
      "candidate_text": ", 640, 480"
    }
  ],
  "203": [
    {
      "state_id": 54,
      "candidate": "NUM",
      "candidate_text": "640"
    }
  ],
  "206": [
    {
      "state_id": 217,
      "candidate": ", MoreThanOneExpr",
      "candidate_text": ", 480"
    }
  ],
  "208": [
    {
      "state_id": 54,
      "candidate": "NUM",
      "candidate_text": "480"
    }
  ],
  "211": [
    {
      "state_id": 238,
      "candidate": ")",
      "candidate_text": ")"
    }
  ],
  "213": [
    {
      "state_id": 206,
      "candidate": "CR_token2",
      "candidate_text": ""
    }
  ],
  "214": [
    {
      "state_id": 257,
      "candidate": "Stmt_token8",
      "candidate_text": "EndSub"
    }
  ]
}