{
  "0": [
    {
      "state_id": 1,
      "candidate": "export declaration",
      "candidate_text": "export function pick<T, K extends keyof T>(container: T, key: K) {"
    }
  ],
  "7": [
    {
      "state_id": 696,
      "candidate": "function identifier _call_signature statement_block _automatic_semicolon",
      "candidate_text": "function pick<T, K extends keyof T>(container: T, key: K) {"
    }
  ],
  "16": [
    {
      "state_id": 5302,
      "candidate": "identifier _call_signature statement_block _automatic_semicolon",
      "candidate_text": "pick<T, K extends keyof T>(container: T, key: K) {"
    }
  ],
  "20": [
    {
      "state_id": 4201,
      "candidate": "< type_parameter type_parameters_repeat1 >",
      "candidate_text": "<T, K extends keyof T>"
    }
  ],
  "21": [
    {
      "state_id": 4996,
      "candidate": "identifier",
      "candidate_text": "T"
    }
  ],
  "22": [
    {
      "state_id": 4908,
      "candidate": ", type_parameter",
      "candidate_text": ", K extends keyof T"
    }
  ],
  "24": [
    {
      "state_id": 4475,
      "candidate": "identifier constraint",
      "candidate_text": "K extends keyof T"
    }
  ],
  "26": [
    {
      "state_id": 3526,
      "candidate": "extends type",
      "candidate_text": "extends keyof T"
    }
  ],
  "34": [
    {
      "state_id": 1056,
      "candidate": "keyof primary_type",
      "candidate_text": "keyof T"
    }
  ],
  "40": [
    {
      "state_id": 1013,
      "candidate": "identifier",
      "candidate_text": "T"
    }
  ],
  "41": [
    {
      "state_id": 4713,
      "candidate": ">",
      "candidate_text": ">"
    }
  ],
  "42": [
    {
      "state_id": 5249,
      "candidate": "( required_parameter formal_parameters_repeat1 )",
      "candidate_text": "(container: T, key: K)"
    }
  ],
  "43": [
    {
      "state_id": 197,
      "candidate": "identifier",
      "candidate_text": "container"
    }
  ],
  "52": [
    {
      "state_id": 3624,
      "candidate": ": type",
      "candidate_text": ": T"
    }
  ],
  "54": [
    {
      "state_id": 1006,
      "candidate": "identifier",
      "candidate_text": "T"
    }
  ],
  "55": [
    {
      "state_id": 4899,
      "candidate": ", required_parameter",
      "candidate_text": ", key: K"
    }
  ],
  "57": [
    {
      "state_id": 205,
      "candidate": "identifier",
      "candidate_text": "key"
    }
  ],
  "60": [
    {
      "state_id": 3624,
      "candidate": ": type",
      "candidate_text": ": K"
    }
  ],
  "62": [
    {
      "state_id": 1006,
      "candidate": "identifier",
      "candidate_text": "K"
    }
  ],
  "63": [
    {
      "state_id": 4869,
      "candidate": ")",
      "candidate_text": ")"
    }
  ],
  "65": [
    {
      "state_id": 4250,
      "candidate": "{ statement } _automatic_semicolon",
      "candidate_text": "{\n\treturn container[key];\n}"
    }
  ],
  "68": [
    {
      "state_id": 28,
      "candidate": "return expression ;",
      "candidate_text": "return container[key];"
    }
  ],
  "75": [
    {
      "state_id": 297,
      "candidate": "identifier",
      "candidate_text": "container"
    }
  ],
  "84": [
    {
      "state_id": 1810,
      "candidate": "[ expression ]",
      "candidate_text": "[key]"
    }
  ],
  "85": [
    {
      "state_id": 327,
      "candidate": "identifier",
      "candidate_text": "key"
    }
  ],
  "88": [
    {
      "state_id": 2225,
      "candidate": "]",
      "candidate_text": "]"
    }
  ],
  "89": [
    {
      "state_id": 1905,
      "candidate": ";",
      "candidate_text": ";"
    }
  ],
  "91": [
    {
      "state_id": 15,
      "candidate": "} _automatic_semicolon",
      "candidate_text": "}"
    }
  ]
}