{
  "2568": [
    {
      "state_id": 1,
      "candidate": "import scoped_identifier ;",
      "candidate_text": "import java.util.Scanner;"
    }
  ],
  "2575": [
    {
      "state_id": 894,
      "candidate": "identifier . identifier",
      "candidate_text": "java.util"
    }
  ],
  "2579": [
    {
      "state_id": 1205,
      "candidate": ". identifier",
      "candidate_text": ".util"
    }
  ],
  "2580": [
    {
      "state_id": 1103,
      "candidate": "identifier",
      "candidate_text": "util"
    }
  ],
  "2584": [
    {
      "state_id": 1205,
      "candidate": ". identifier",
      "candidate_text": ".Scanner"
    }
  ],
  "2585": [
    {
      "state_id": 1103,
      "candidate": "identifier",
      "candidate_text": "Scanner"
    }
  ],
  "2592": [
    {
      "state_id": 1205,
      "candidate": ";",
      "candidate_text": ";"
    }
  ],
  "2595": [
    {
      "state_id": 3,
      "candidate": "public",
      "candidate_text": "public"
    }
  ],
  "2602": [
    {
      "state_id": 727,
      "candidate": "class identifier class_body",
      "candidate_text": "class Exercise_06_31 {"
    }
  ],
  "2608": [
    {
      "state_id": 1307,
      "candidate": "identifier class_body",
      "candidate_text": "Exercise_06_31 {"
    }
  ],
  "2623": [
    {
      "state_id": 896,
      "candidate": "{ enum_body_declarations_repeat1 }",
      "candidate_text": "{\n\t/** Main Method */"
    }
  ],
  "2626": [
    {
      "state_id": 408,
      "candidate": "enum_body_declarations_repeat1 }",
      "candidate_text": "/** Main Method */"
    }
  ],
  "2646": [
    {
      "state_id": 408,
      "candidate": "public static",
      "candidate_text": "public static"
    }
  ],
  "2653": [
    {
      "state_id": 505,
      "candidate": "static",
      "candidate_text": "static"
    }
  ],
  "2660": [
    {
      "state_id": 698,
      "candidate": "void_type",
      "candidate_text": "void"
    }
  ],
  "2665": [
    {
      "state_id": 784,
      "candidate": "identifier formal_parameters",
      "candidate_text": "main(String[] args)"
    }
  ],
  "2669": [
    {
      "state_id": 867,
      "candidate": "( formal_parameter )",
      "candidate_text": "(String[] args)"
    }
  ],
  "2670": [
    {
      "state_id": 471,
      "candidate": "identifier",
      "candidate_text": "String"
    }
  ],
  "2676": [
    {
      "state_id": 782,
      "candidate": "[ ]",
      "candidate_text": "[]"
    }
  ],
  "2677": [
    {
      "state_id": 1354,
      "candidate": "]",
      "candidate_text": "]"
    }
  ],
  "2679": [
    {
      "state_id": 782,
      "candidate": "identifier",
      "candidate_text": "args"
    }
  ],
  "2683": [
    {
      "state_id": 1076,
      "candidate": ")",
      "candidate_text": ")"
    }
  ],
  "2685": [
    {
      "state_id": 1117,
      "candidate": "{ switch_block_statement_group_repeat2 }",
      "candidate_text": "{\n\t\tScanner input = new Scanner(System.in); // Create a Scanner"
    }
  ],
  "2689": [
    {
      "state_id": 9,
      "candidate": "identifier",
      "candidate_text": "Scanner"
    }
  ],
  "2697": [
    {
      "state_id": 775,
      "candidate": "identifier",
      "candidate_text": "input"
    }
  ],
  "2703": [
    {
      "state_id": 1058,
      "candidate": "= expression",
      "candidate_text": "= new Scanner(System.in)"
    }
  ],
  "2705": [
    {
      "state_id": 146,
      "candidate": "new identifier argument_list",
      "candidate_text": "new Scanner(System.in)"
    }
  ],
  "2709": [
    {
      "state_id": 785,
      "candidate": "identifier argument_list",
      "candidate_text": "Scanner(System.in)"
    }
  ],
  "2716": [
    {
      "state_id": 853,
      "candidate": "( expression )",
      "candidate_text": "(System.in)"
    }
  ],
  "2717": [
    {
      "state_id": 155,
      "candidate": "identifier",
      "candidate_text": "System"
    }
  ],
  "2723": [
    {
      "state_id": 549,
      "candidate": ". identifier",
      "candidate_text": ".in"
    }
  ],
  "2724": [
    {
      "state_id": 811,
      "candidate": "identifier",
      "candidate_text": "in"
    }
  ],
  "2726": [
    {
      "state_id": 662,
      "candidate": ")",
      "candidate_text": ")"
    }
  ],
  "2727": [
    {
      "state_id": 1369,
      "candidate": ";",
      "candidate_text": ";"
    }
  ],
  "2731": [
    {
      "state_id": 8,
      "candidate": "statement",
      "candidate_text": " Create a Scanner"
    }
  ],
  "2751": [
    {
      "state_id": 8,
      "candidate": "statement",
      "candidate_text": "\t// Prompt the user to enter a credit card number as a long integer"
    }
  ],
  "2821": [
    {
      "state_id": 8,
      "candidate": "identifier",
      "candidate_text": "System"
    }
  ],
  "2827": [
    {
      "state_id": 549,
      "candidate": ". identifier",
      "candidate_text": ".out"
    }
  ],
  "2828": [
    {
      "state_id": 811,
      "candidate": "identifier",
      "candidate_text": "out"
    }
  ],
  "2831": [
    {
      "state_id": 549,
      "candidate": ". identifier argument_list",
      "candidate_text": ".print(\"Enter a credit card number as a long integer: \")"
    }
  ],
  "2832": [
    {
      "state_id": 811,
      "candidate": "identifier argument_list",
      "candidate_text": "print(\"Enter a credit card number as a long integer: \")"
    }
  ],
  "2837": [
    {
      "state_id": 429,
      "candidate": "( expression )",
      "candidate_text": "(\"Enter a credit card number as a long integer: \")"
    }
  ],
  "2838": [
    {
      "state_id": 155,
      "candidate": "\" string_fragment \"",
      "candidate_text": "\"Enter a credit card number as a long integer: \""
    }
  ],
  "2839": [
    {
      "state_id": 978,
      "candidate": "string_fragment \"",
      "candidate_text": "Enter a credit card number as a long integer: \""
    }
  ],
  "2885": [
    {
      "state_id": 962,
      "candidate": "\"",
      "candidate_text": "\""
    }
  ],
  "2886": [
    {
      "state_id": 662,
      "candidate": ")",
      "candidate_text": ")"
    }
  ],
  "2887": [
    {
      "state_id": 752,
      "candidate": ";",
      "candidate_text": ";"
    }
  ],
  "2891": [
    {
      "state_id": 8,
      "candidate": "long",
      "candidate_text": "long"
    }
  ],
  "2896": [
    {
      "state_id": 775,
      "candidate": "identifier",
      "candidate_text": "number"
    }
  ],
  "2903": [
    {
      "state_id": 1058,
      "candidate": "= expression",
      "candidate_text": "= input.nextLong()"
    }
  ],
  "2905": [
    {
      "state_id": 146,
      "candidate": "identifier",
      "candidate_text": "input"
    }
  ],
  "2910": [
    {
      "state_id": 549,
      "candidate": ". identifier argument_list",
      "candidate_text": ".nextLong()"
    }
  ],
  "2911": [
    {
      "state_id": 811,
      "candidate": "identifier argument_list",
      "candidate_text": "nextLong()"
    }
  ],
  "2919": [
    {
      "state_id": 429,
      "candidate": "( )",
      "candidate_text": "()"
    }
  ],
  "2920": [
    {
      "state_id": 155,
      "candidate": ")",
      "candidate_text": ")"
    }
  ],
  "2921": [
    {
      "state_id": 1369,
      "candidate": ";",
      "candidate_text": ";"
    }
  ],
  "2926": [
    {
      "state_id": 8,
      "candidate": "identifier",
      "candidate_text": "System"
    }
  ],
  "2932": [
    {
      "state_id": 549,
      "candidate": ". identifier",
      "candidate_text": ".out"
    }
  ],
  "2933": [
    {
      "state_id": 811,
      "candidate": "identifier",
      "candidate_text": "out"
    }
  ],
  "2936": [
    {
      "state_id": 549,
      "candidate": ". identifier argument_list",
      "candidate_text": ".println("
    }
  ],
  "2937": [
    {
      "state_id": 811,
      "candidate": "identifier argument_list",
      "candidate_text": "println("
    }
  ],
  "2944": [
    {
      "state_id": 429,
      "candidate": "( expression )",
      "candidate_text": "(\n\t\t\tnumber + \" is \" + (isValid(number) ? \"valid\" : \"invalid\"))"
    }
  ],
  "2949": [
    {
      "state_id": 155,
      "candidate": "identifier",
      "candidate_text": "number"
    }
  ],
  "2956": [
    {
      "state_id": 662,
      "candidate": "+ expression",
      "candidate_text": "+ \" is \""
    }
  ],
  "2958": [
    {
      "state_id": 234,
      "candidate": "\" string_fragment \"",
      "candidate_text": "\" is \""
    }
  ],
  "2959": [
    {
      "state_id": 978,
      "candidate": "string_fragment \"",
      "candidate_text": " is \""
    }
  ],
  "2963": [
    {
      "state_id": 962,
      "candidate": "\"",
      "candidate_text": "\""
    }
  ],
  "2965": [
    {
      "state_id": 662,
      "candidate": "+ expression",
      "candidate_text": "+ (isValid(number) ? \"valid\" : \"invalid\")"
    }
  ],
  "2967": [
    {
      "state_id": 234,
      "candidate": "( expression )",
      "candidate_text": "(isValid(number) ? \"valid\" : \"invalid\")"
    }
  ],
  "2968": [
    {
      "state_id": 115,
      "candidate": "identifier argument_list",
      "candidate_text": "isValid(number)"
    }
  ],
  "2975": [
    {
      "state_id": 415,
      "candidate": "( expression )",
      "candidate_text": "(number)"
    }
  ],
  "2976": [
    {
      "state_id": 155,
      "candidate": "identifier",
      "candidate_text": "number"
    }
  ],
  "2982": [
    {
      "state_id": 662,
      "candidate": ")",
      "candidate_text": ")"
    }
  ],
  "2984": [
    {
      "state_id": 757,
      "candidate": "? expression : expression",
      "candidate_text": "? \"valid\" : \"invalid\""
    }
  ],
  "2986": [
    {
      "state_id": 239,
      "candidate": "\" string_fragment \"",
      "candidate_text": "\"valid\""
    }
  ],
  "2987": [
    {
      "state_id": 978,
      "candidate": "string_fragment \"",
      "candidate_text": "valid\""
    }
  ],
  "2992": [
    {
      "state_id": 962,
      "candidate": "\"",
      "candidate_text": "\""
    }
  ],
  "2994": [
    {
      "state_id": 728,
      "candidate": ": expression",
      "candidate_text": ": \"invalid\""
    }
  ],
  "2996": [
    {
      "state_id": 200,
      "candidate": "\" string_fragment \"",
      "candidate_text": "\"invalid\""
    }
  ],
  "2997": [
    {
      "state_id": 978,
      "candidate": "string_fragment \"",
      "candidate_text": "invalid\""
    }
  ],
  "3004": [
    {
      "state_id": 962,
      "candidate": "\"",
      "candidate_text": "\""
    }
  ],
  "3005": [
    {
      "state_id": 757,
      "candidate": ")",
      "candidate_text": ")"
    }
  ],
  "3006": [
    {
      "state_id": 662,
      "candidate": ")",
      "candidate_text": ")"
    }
  ],
  "3007": [
    {
      "state_id": 752,
      "candidate": ";",
      "candidate_text": ";"
    }
  ],
  "3010": [
    {
      "state_id": 8,
      "candidate": "}",
      "candidate_text": "}"
    }
  ],
  "3013": [
    {
      "state_id": 410,
      "candidate": "method_declaration",
      "candidate_text": "\t/** Return true if the card number is valid */"
    }
  ],
  "3062": [
    {
      "state_id": 410,
      "candidate": "public static",
      "candidate_text": "public static"
    }
  ],
  "3069": [
    {
      "state_id": 505,
      "candidate": "static",
      "candidate_text": "static"
    }
  ],
  "3076": [
    {
      "state_id": 698,
      "candidate": "boolean_type",
      "candidate_text": "boolean"
    }
  ],
  "3084": [
    {
      "state_id": 784,
      "candidate": "identifier formal_parameters",
      "candidate_text": "isValid(long number)"
    }
  ],
  "3091": [
    {
      "state_id": 867,
      "candidate": "( formal_parameter )",
      "candidate_text": "(long number)"
    }
  ],
  "3092": [
    {
      "state_id": 471,
      "candidate": "long",
      "candidate_text": "long"
    }
  ],
  "3097": [
    {
      "state_id": 782,
      "candidate": "identifier",
      "candidate_text": "number"
    }
  ],
  "3103": [
    {
      "state_id": 1076,
      "candidate": ")",
      "candidate_text": ")"
    }
  ],
  "3105": [
    {
      "state_id": 1117,
      "candidate": "{ switch_block_statement_group_repeat2 }",
      "candidate_text": "{\n\t\tboolean valid ="
    }
  ],
  "3109": [
    {
      "state_id": 9,
      "candidate": "boolean_type",
      "candidate_text": "boolean"
    }
  ],
  "3117": [
    {
      "state_id": 775,
      "candidate": "identifier",
      "candidate_text": "valid"
    }
  ],
  "3123": [
    {
      "state_id": 1058,
      "candidate": "= expression",
      "candidate_text": "=\n\t\t\t(getSize(number) >= 13 && getSize(number) <= 16) &&"
    }
  ],
  "3128": [
    {
      "state_id": 146,
      "candidate": "( expression )",
      "candidate_text": "(getSize(number) >= 13 && getSize(number) <= 16)"
    }
  ],
  "3129": [
    {
      "state_id": 115,
      "candidate": "identifier argument_list",
      "candidate_text": "getSize(number)"
    }
  ],
  "3136": [
    {
      "state_id": 415,
      "candidate": "( expression )",
      "candidate_text": "(number)"
    }
  ],
  "3137": [
    {
      "state_id": 155,
      "candidate": "identifier",
      "candidate_text": "number"
    }
  ],
  "3143": [
    {
      "state_id": 662,
      "candidate": ")",
      "candidate_text": ")"
    }
  ],
  "3145": [
    {
      "state_id": 757,
      "candidate": ">= expression",
      "candidate_text": ">= 13"
    }
  ],
  "3148": [
    {
      "state_id": 230,
      "candidate": "decimal_integer_literal",
      "candidate_text": "13"
    }
  ],
  "3151": [
    {
      "state_id": 757,
      "candidate": "&& expression",
      "candidate_text": "&& getSize(number) <= 16"
    }
  ],
  "3154": [
    {
      "state_id": 232,
      "candidate": "identifier argument_list",
      "candidate_text": "getSize(number)"
    }
  ],
  "3161": [
    {
      "state_id": 413,
      "candidate": "( expression )",
      "candidate_text": "(number)"
    }
  ],
  "3162": [
    {
      "state_id": 155,
      "candidate": "identifier",
      "candidate_text": "number"
    }
  ],
  "3168": [
    {
      "state_id": 662,
      "candidate": ")",
      "candidate_text": ")"
    }
  ],
  "3170": [
    {
      "state_id": 620,
      "candidate": "<= expression",
      "candidate_text": "<= 16"
    }
  ],
  "3173": [
    {
      "state_id": 230,
      "candidate": "decimal_integer_literal",
      "candidate_text": "16"
    }
  ],
  "3175": [
    {
      "state_id": 757,
      "candidate": ")",
      "candidate_text": ")"
    }
  ],
  "3177": [
    {
      "state_id": 668,
      "candidate": "&& expression",
      "candidate_text": "&&\n\t\t\t(prefixMatched(number, 4) || prefixMatched(number, 5) ||"
    }
  ],
  "3183": [
    {
      "state_id": 232,
      "candidate": "( expression )",
      "candidate_text": "(prefixMatched(number, 4) || prefixMatched(number, 5) ||\n\t\t\tprefixMatched(number, 37) || prefixMatched(number, 6))"
    }
  ],
  "3184": [
    {
      "state_id": 115,
      "candidate": "identifier argument_list",
      "candidate_text": "prefixMatched(number, 4)"
    }
  ],
  "3197": [
    {
      "state_id": 415,
      "candidate": "( expression argument_list_repeat1 )",
      "candidate_text": "(number, 4)"
    }
  ],
  "3198": [
    {
      "state_id": 155,
      "candidate": "identifier",
      "candidate_text": "number"
    }
  ],
  "3204": [
    {
      "state_id": 662,
      "candidate": ", expression",
      "candidate_text": ", 4"
    }
  ],
  "3206": [
    {
      "state_id": 199,
      "candidate": "decimal_integer_literal",
      "candidate_text": "4"
    }
  ],
  "3207": [
    {
      "state_id": 1169,
      "candidate": ")",
      "candidate_text": ")"
    }
  ],
  "3209": [
    {
      "state_id": 757,
      "candidate": "|| expression",
      "candidate_text": "|| prefixMatched(number, 5)"
    }
  ],
  "3212": [
    {
      "state_id": 233,
      "candidate": "identifier argument_list",
      "candidate_text": "prefixMatched(number, 5)"
    }
  ],
  "3225": [
    {
      "state_id": 413,
      "candidate": "( expression argument_list_repeat1 )",
      "candidate_text": "(number, 5)"
    }
  ],
  "3226": [
    {
      "state_id": 155,
      "candidate": "identifier",
      "candidate_text": "number"
    }
  ],
  "3232": [
    {
      "state_id": 662,
      "candidate": ", expression",
      "candidate_text": ", 5"
    }
  ],
  "3234": [
    {
      "state_id": 199,
      "candidate": "decimal_integer_literal",
      "candidate_text": "5"
    }
  ],
  "3235": [
    {
      "state_id": 1169,
      "candidate": ")",
      "candidate_text": ")"
    }
  ],
  "3237": [
    {
      "state_id": 757,
      "candidate": "|| expression",
      "candidate_text": "||\n\t\t\tprefixMatched(number, 37)"
    }
  ],
  "3243": [
    {
      "state_id": 233,
      "candidate": "identifier argument_list",
      "candidate_text": "prefixMatched(number, 37)"
    }
  ],
  "3256": [
    {
      "state_id": 413,
      "candidate": "( expression argument_list_repeat1 )",
      "candidate_text": "(number, 37)"
    }
  ],
  "3257": [
    {
      "state_id": 155,
      "candidate": "identifier",
      "candidate_text": "number"
    }
  ],
  "3263": [
    {
      "state_id": 662,
      "candidate": ", expression",
      "candidate_text": ", 37"
    }
  ],
  "3265": [
    {
      "state_id": 199,
      "candidate": "decimal_integer_literal",
      "candidate_text": "37"
    }
  ],
  "3267": [
    {
      "state_id": 1169,
      "candidate": ")",
      "candidate_text": ")"
    }
  ],
  "3269": [
    {
      "state_id": 757,
      "candidate": "|| expression",
      "candidate_text": "|| prefixMatched(number, 6)"
    }
  ],
  "3272": [
    {
      "state_id": 233,
      "candidate": "identifier argument_list",
      "candidate_text": "prefixMatched(number, 6)"
    }
  ],
  "3285": [
    {
      "state_id": 413,
      "candidate": "( expression argument_list_repeat1 )",
      "candidate_text": "(number, 6)"
    }
  ],
  "3286": [
    {
      "state_id": 155,
      "candidate": "identifier",
      "candidate_text": "number"
    }
  ],
  "3292": [
    {
      "state_id": 662,
      "candidate": ", expression",
      "candidate_text": ", 6"
    }
  ],
  "3294": [
    {
      "state_id": 199,
      "candidate": "decimal_integer_literal",
      "candidate_text": "6"
    }
  ],
  "3295": [
    {
      "state_id": 1169,
      "candidate": ")",
      "candidate_text": ")"
    }
  ],
  "3296": [
    {
      "state_id": 757,
      "candidate": ")",
      "candidate_text": ")"
    }
  ],
  "3298": [
    {
      "state_id": 668,
      "candidate": "&& expression",
      "candidate_text": "&&\n\t\t\t((sumOfDoubleEvenPlace(number) + sumOfOddPlace(number)) % 10 == 0)"
    }
  ],
  "3304": [
    {
      "state_id": 232,
      "candidate": "( expression )",
      "candidate_text": "((sumOfDoubleEvenPlace(number) + sumOfOddPlace(number)) % 10 == 0)"
    }
  ],
  "3305": [
    {
      "state_id": 115,
      "candidate": "( expression )",
      "candidate_text": "(sumOfDoubleEvenPlace(number) + sumOfOddPlace(number))"
    }
  ],
  "3306": [
    {
      "state_id": 115,
      "candidate": "identifier argument_list",
      "candidate_text": "sumOfDoubleEvenPlace(number)"
    }
  ],
  "3326": [
    {
      "state_id": 415,
      "candidate": "( expression )",
      "candidate_text": "(number)"
    }
  ],
  "3327": [
    {
      "state_id": 155,
      "candidate": "identifier",
      "candidate_text": "number"
    }
  ],
  "3333": [
    {
      "state_id": 662,
      "candidate": ")",
      "candidate_text": ")"
    }
  ],
  "3335": [
    {
      "state_id": 757,
      "candidate": "+ expression",
      "candidate_text": "+ sumOfOddPlace(number)"
    }
  ],
  "3337": [
    {
      "state_id": 234,
      "candidate": "identifier argument_list",
      "candidate_text": "sumOfOddPlace(number)"
    }
  ],
  "3350": [
    {
      "state_id": 413,
      "candidate": "( expression )",
      "candidate_text": "(number)"
    }
  ],
  "3351": [
    {
      "state_id": 155,
      "candidate": "identifier",
      "candidate_text": "number"
    }
  ],
  "3357": [
    {
      "state_id": 662,
      "candidate": ")",
      "candidate_text": ")"
    }
  ],
  "3358": [
    {
      "state_id": 757,
      "candidate": ")",
      "candidate_text": ")"
    }
  ],
  "3360": [
    {
      "state_id": 757,
      "candidate": "% expression",
      "candidate_text": "% 10"
    }
  ],
  "3362": [
    {
      "state_id": 235,
      "candidate": "decimal_integer_literal",
      "candidate_text": "10"
    }
  ],
  "3365": [
    {
      "state_id": 757,
      "candidate": "== expression",
      "candidate_text": "== 0"
    }
  ],
  "3368": [
    {
      "state_id": 231,
      "candidate": "decimal_integer_literal",
      "candidate_text": "0"
    }
  ],
  "3369": [
    {
      "state_id": 757,
      "candidate": ")",
      "candidate_text": ")"
    }
  ],
  "3370": [
    {
      "state_id": 1369,
      "candidate": ";",
      "candidate_text": ";"
    }
  ],
  "3375": [
    {
      "state_id": 8,
      "candidate": "return expression ;",
      "candidate_text": "return valid;"
    }
  ],
  "3382": [
    {
      "state_id": 149,
      "candidate": "identifier",
      "candidate_text": "valid"
    }
  ],
  "3387": [
    {
      "state_id": 729,
      "candidate": ";",
      "candidate_text": ";"
    }
  ],
  "3390": [
    {
      "state_id": 8,
      "candidate": "}",
      "candidate_text": "}"
    }
  ],
  "3393": [
    {
      "state_id": 410,
      "candidate": "method_declaration",
      "candidate_text": ""
    }
  ],
  "3430": [
    {
      "state_id": 410,
      "candidate": "public static",
      "candidate_text": "public static"
    }
  ],
  "3437": [
    {
      "state_id": 505,
      "candidate": "static",
      "candidate_text": "static"
    }
  ],
  "3444": [
    {
      "state_id": 698,
      "candidate": "int",
      "candidate_text": "int"
    }
  ],
  "3448": [
    {
      "state_id": 784,
      "candidate": "identifier formal_parameters",
      "candidate_text": "sumOfDoubleEvenPlace(long number)"
    }
  ],
  "3468": [
    {
      "state_id": 867,
      "candidate": "( formal_parameter )",
      "candidate_text": "(long number)"
    }
  ],
  "3469": [
    {
      "state_id": 471,
      "candidate": "long",
      "candidate_text": "long"
    }
  ],
  "3474": [
    {
      "state_id": 782,
      "candidate": "identifier",
      "candidate_text": "number"
    }
  ],
  "3480": [
    {
      "state_id": 1076,
      "candidate": ")",
      "candidate_text": ")"
    }
  ],
  "3482": [
    {
      "state_id": 1117,
      "candidate": "{ switch_block_statement_group_repeat2 }",
      "candidate_text": "{\n\t\tint sum = 0;\n\t\tString num = number + \"\";\n\t\tfor (int i = getSize(number) - 2; i >= 0; i -= 2) {\n\t\t\tsum += getDigit(Integer.parseInt(num.charAt(i) + \"\") * 2);\n\t\t}\n\t\treturn sum;\n\t}"
    }
  ],
  "3486": [
    {
      "state_id": 9,
      "candidate": "int",
      "candidate_text": "int"
    }
  ],
  "3490": [
    {
      "state_id": 775,
      "candidate": "identifier",
      "candidate_text": "sum"
    }
  ],
  "3494": [
    {
      "state_id": 1058,
      "candidate": "= expression",
      "candidate_text": "= 0"
    }
  ],
  "3496": [
    {
      "state_id": 146,
      "candidate": "decimal_integer_literal",
      "candidate_text": "0"
    }
  ],
  "3497": [
    {
      "state_id": 1369,
      "candidate": ";",
      "candidate_text": ";"
    }
  ],
  "3501": [
    {
      "state_id": 8,
      "candidate": "identifier",
      "candidate_text": "String"
    }
  ],
  "3508": [
    {
      "state_id": 775,
      "candidate": "identifier",
      "candidate_text": "num"
    }
  ],
  "3512": [
    {
      "state_id": 1058,
      "candidate": "= expression",
      "candidate_text": "= number + \"\""
    }
  ],
  "3514": [
    {
      "state_id": 146,
      "candidate": "identifier",
      "candidate_text": "number"
    }
  ],
  "3521": [
    {
      "state_id": 668,
      "candidate": "+ expression",
      "candidate_text": "+ \"\""
    }
  ],
  "3523": [
    {
      "state_id": 234,
      "candidate": "\" \"",
      "candidate_text": "\"\""
    }
  ],
  "3524": [
    {
      "state_id": 978,
      "candidate": "\"",
      "candidate_text": "\""
    }
  ],
  "3525": [
    {
      "state_id": 1369,
      "candidate": ";",
      "candidate_text": ";"
    }
  ],
  "3529": [
    {
      "state_id": 8,
      "candidate": "for ( local_variable_declaration expression ; expression ) statement",
      "candidate_text": "for (int i = getSize(number) - 2; i >= 0; i -= 2) {"
    }
  ],
  "3533": [
    {
      "state_id": 1376,
      "candidate": "( local_variable_declaration expression ; expression ) statement",
      "candidate_text": "(int i = getSize(number) - 2; i >= 0; i -= 2) {"
    }
  ],
  "3534": [
    {
      "state_id": 120,
      "candidate": "int",
      "candidate_text": "int"
    }
  ],
  "3538": [
    {
      "state_id": 780,
      "candidate": "identifier",
      "candidate_text": "i"
    }
  ],
  "3540": [
    {
      "state_id": 1066,
      "candidate": "= expression",
      "candidate_text": "= getSize(number) - 2"
    }
  ],
  "3542": [
    {
      "state_id": 146,
      "candidate": "identifier argument_list",
      "candidate_text": "getSize(number)"
    }
  ],
  "3549": [
    {
      "state_id": 413,
      "candidate": "( expression )",
      "candidate_text": "(number)"
    }
  ],
  "3550": [
    {
      "state_id": 155,
      "candidate": "identifier",
      "candidate_text": "number"
    }
  ],
  "3556": [
    {
      "state_id": 662,
      "candidate": ")",
      "candidate_text": ")"
    }
  ],
  "3558": [
    {
      "state_id": 668,
      "candidate": "- expression",
      "candidate_text": "- 2"
    }
  ],
  "3560": [
    {
      "state_id": 234,
      "candidate": "decimal_integer_literal",
      "candidate_text": "2"
    }
  ],
  "3561": [
    {
      "state_id": 1368,
      "candidate": ";",
      "candidate_text": ";"
    }
  ],
  "3563": [
    {
      "state_id": 182,
      "candidate": "identifier",
      "candidate_text": "i"
    }
  ],
  "3565": [
    {
      "state_id": 750,
      "candidate": ">= expression",
      "candidate_text": ">= 0"
    }
  ],
  "3568": [
    {
      "state_id": 230,
      "candidate": "decimal_integer_literal",
      "candidate_text": "0"
    }
  ],
  "3569": [
    {
      "state_id": 750,
      "candidate": "; expression ) statement",
      "candidate_text": "; i -= 2) {"
    }
  ],
  "3571": [
    {
      "state_id": 169,
      "candidate": "identifier -= expression",
      "candidate_text": "i -= 2"
    }
  ],
  "3573": [
    {
      "state_id": 413,
      "candidate": "-= expression",
      "candidate_text": "-= 2"
    }
  ],
  "3576": [
    {
      "state_id": 228,
      "candidate": "decimal_integer_literal",
      "candidate_text": "2"
    }
  ],
  "3577": [
    {
      "state_id": 678,
      "candidate": ") statement",
      "candidate_text": ") {"
    }
  ],
  "3579": [
    {
      "state_id": 63,
      "candidate": "{ statement }",
      "candidate_text": "{\n\t\t\tsum += getDigit(Integer.parseInt(num.charAt(i) + \"\") * 2);\n\t\t}"
    }
  ],
  "3584": [
    {
      "state_id": 9,
      "candidate": "identifier += expression",
      "candidate_text": "sum += getDigit(Integer.parseInt(num.charAt(i) + \"\") * 2)"
    }
  ],
  "3588": [
    {
      "state_id": 421,
      "candidate": "+= expression",
      "candidate_text": "+= getDigit(Integer.parseInt(num.charAt(i) + \"\") * 2)"
    }
  ],
  "3591": [
    {
      "state_id": 228,
      "candidate": "identifier argument_list",
      "candidate_text": "getDigit(Integer.parseInt(num.charAt(i) + \"\") * 2)"
    }
  ],
  "3599": [
    {
      "state_id": 413,
      "candidate": "( expression )",
      "candidate_text": "(Integer.parseInt(num.charAt(i) + \"\") * 2)"
    }
  ],
  "3600": [
    {
      "state_id": 155,
      "candidate": "identifier",
      "candidate_text": "Integer"
    }
  ],
  "3607": [
    {
      "state_id": 549,
      "candidate": ". identifier argument_list",
      "candidate_text": ".parseInt(num.charAt(i) + \"\")"
    }
  ],
  "3608": [
    {
      "state_id": 811,
      "candidate": "identifier argument_list",
      "candidate_text": "parseInt(num.charAt(i) + \"\")"
    }
  ],
  "3616": [
    {
      "state_id": 429,
      "candidate": "( expression )",
      "candidate_text": "(num.charAt(i) + \"\")"
    }
  ],
  "3617": [
    {
      "state_id": 155,
      "candidate": "identifier",
      "candidate_text": "num"
    }
  ],
  "3620": [
    {
      "state_id": 549,
      "candidate": ". identifier argument_list",
      "candidate_text": ".charAt(i)"
    }
  ],
  "3621": [
    {
      "state_id": 811,
      "candidate": "identifier argument_list",
      "candidate_text": "charAt(i)"
    }
  ],
  "3627": [
    {
      "state_id": 429,
      "candidate": "( expression )",
      "candidate_text": "(i)"
    }
  ],
  "3628": [
    {
      "state_id": 155,
      "candidate": "identifier",
      "candidate_text": "i"
    }
  ],
  "3629": [
    {
      "state_id": 662,
      "candidate": ")",
      "candidate_text": ")"
    }
  ],
  "3631": [
    {
      "state_id": 662,
      "candidate": "+ expression",
      "candidate_text": "+ \"\""
    }
  ],
  "3633": [
    {
      "state_id": 234,
      "candidate": "\" \"",
      "candidate_text": "\"\""
    }
  ],
  "3634": [
    {
      "state_id": 978,
      "candidate": "\"",
      "candidate_text": "\""
    }
  ],
  "3635": [
    {
      "state_id": 662,
      "candidate": ")",
      "candidate_text": ")"
    }
  ],
  "3637": [
    {
      "state_id": 662,
      "candidate": "* expression",
      "candidate_text": "* 2"
    }
  ],
  "3639": [
    {
      "state_id": 235,
      "candidate": "decimal_integer_literal",
      "candidate_text": "2"
    }
  ],
  "3640": [
    {
      "state_id": 662,
      "candidate": ")",
      "candidate_text": ")"
    }
  ],
  "3641": [
    {
      "state_id": 752,
      "candidate": ";",
      "candidate_text": ";"
    }
  ],
  "3645": [
    {
      "state_id": 8,
      "candidate": "}",
      "candidate_text": "}"
    }
  ],
  "3649": [
    {
      "state_id": 8,
      "candidate": "return expression ;",
      "candidate_text": "return sum;"
    }
  ],
  "3656": [
    {
      "state_id": 149,
      "candidate": "identifier",
      "candidate_text": "sum"
    }
  ],
  "3659": [
    {
      "state_id": 729,
      "candidate": ";",
      "candidate_text": ";"
    }
  ],
  "3662": [
    {
      "state_id": 8,
      "candidate": "}",
      "candidate_text": "}"
    }
  ],
  "3665": [
    {
      "state_id": 410,
      "candidate": "enum_body_declarations_repeat1",
      "candidate_text": ""
    }
  ],
  "3766": [
    {
      "state_id": 410,
      "candidate": "public static",
      "candidate_text": "public static"
    }
  ],
  "3773": [
    {
      "state_id": 505,
      "candidate": "static",
      "candidate_text": "static"
    }
  ],
  "3780": [
    {
      "state_id": 698,
      "candidate": "int",
      "candidate_text": "int"
    }
  ],
  "3784": [
    {
      "state_id": 784,
      "candidate": "identifier formal_parameters",
      "candidate_text": "getDigit(int number)"
    }
  ],
  "3792": [
    {
      "state_id": 867,
      "candidate": "( formal_parameter )",
      "candidate_text": "(int number)"
    }
  ],
  "3793": [
    {
      "state_id": 471,
      "candidate": "int",
      "candidate_text": "int"
    }
  ],
  "3797": [
    {
      "state_id": 782,
      "candidate": "identifier",
      "candidate_text": "number"
    }
  ],
  "3803": [
    {
      "state_id": 1076,
      "candidate": ")",
      "candidate_text": ")"
    }
  ],
  "3805": [
    {
      "state_id": 1117,
      "candidate": "{ statement }",
      "candidate_text": "{\n\t\tif (number < 9)\n\t\t\treturn number;\n\t\telse\n\t\t\treturn number / 10 + number % 10;\n\t}"
    }
  ],
  "3809": [
    {
      "state_id": 9,
      "candidate": "if parenthesized_expression statement else statement",
      "candidate_text": "if (number < 9)\n\t\t\treturn number;\n\t\telse\n\t\t\treturn number / 10 + number % 10;"
    }
  ],
  "3812": [
    {
      "state_id": 1236,
      "candidate": "( expression )",
      "candidate_text": "(number < 9)"
    }
  ],
  "3813": [
    {
      "state_id": 227,
      "candidate": "identifier",
      "candidate_text": "number"
    }
  ],
  "3820": [
    {
      "state_id": 757,
      "candidate": "< expression",
      "candidate_text": "< 9"
    }
  ],
  "3822": [
    {
      "state_id": 230,
      "candidate": "decimal_integer_literal",
      "candidate_text": "9"
    }
  ],
  "3823": [
    {
      "state_id": 757,
      "candidate": ")",
      "candidate_text": ")"
    }
  ],
  "3828": [
    {
      "state_id": 48,
      "candidate": "return expression ;",
      "candidate_text": "return number;"
    }
  ],
  "3835": [
    {
      "state_id": 149,
      "candidate": "identifier",
      "candidate_text": "number"
    }
  ],
  "3841": [
    {
      "state_id": 729,
      "candidate": ";",
      "candidate_text": ";"
    }
  ],
  "3845": [
    {
      "state_id": 392,
      "candidate": "else statement",
      "candidate_text": "else\n\t\t\treturn number / 10 + number % 10;"
    }
  ],
  "3853": [
    {
      "state_id": 50,
      "candidate": "return expression ;",
      "candidate_text": "return number / 10 + number % 10;"
    }
  ],
  "3860": [
    {
      "state_id": 149,
      "candidate": "identifier",
      "candidate_text": "number"
    }
  ],
  "3867": [
    {
      "state_id": 729,
      "candidate": "/ expression",
      "candidate_text": "/ 10"
    }
  ],
  "3869": [
    {
      "state_id": 235,
      "candidate": "decimal_integer_literal",
      "candidate_text": "10"
    }
  ],
  "3872": [
    {
      "state_id": 729,
      "candidate": "+ expression",
      "candidate_text": "+ number % 10"
    }
  ],
  "3874": [
    {
      "state_id": 234,
      "candidate": "identifier",
      "candidate_text": "number"
    }
  ],
  "3881": [
    {
      "state_id": 617,
      "candidate": "% expression",
      "candidate_text": "% 10"
    }
  ],
  "3883": [
    {
      "state_id": 235,
      "candidate": "decimal_integer_literal",
      "candidate_text": "10"
    }
  ],
  "3885": [
    {
      "state_id": 729,
      "candidate": ";",
      "candidate_text": ";"
    }
  ],
  "3888": [
    {
      "state_id": 8,
      "candidate": "}",
      "candidate_text": "}"
    }
  ],
  "3891": [
    {
      "state_id": 412,
      "candidate": "method_declaration",
      "candidate_text": ""
    }
  ],
  "3942": [
    {
      "state_id": 410,
      "candidate": "public static",
      "candidate_text": "public static"
    }
  ],
  "3949": [
    {
      "state_id": 505,
      "candidate": "static",
      "candidate_text": "static"
    }
  ],
  "3956": [
    {
      "state_id": 698,
      "candidate": "int",
      "candidate_text": "int"
    }
  ],
  "3960": [
    {
      "state_id": 784,
      "candidate": "identifier formal_parameters",
      "candidate_text": "sumOfOddPlace(long number)"
    }
  ],
  "3973": [
    {
      "state_id": 867,
      "candidate": "( formal_parameter )",
      "candidate_text": "(long number)"
    }
  ],
  "3974": [
    {
      "state_id": 471,
      "candidate": "long",
      "candidate_text": "long"
    }
  ],
  "3979": [
    {
      "state_id": 782,
      "candidate": "identifier",
      "candidate_text": "number"
    }
  ],
  "3985": [
    {
      "state_id": 1076,
      "candidate": ")",
      "candidate_text": ")"
    }
  ],
  "3987": [
    {
      "state_id": 1117,
      "candidate": "{ switch_block_statement_group_repeat2 }",
      "candidate_text": "{\n\t\tint sum = 0;\n\t\tString num = number + \"\";\n\t\tfor (int i = getSize(number) - 1; i >= 0; i -= 2) {\n\t\t\tsum += Integer.parseInt(num.charAt(i) + \"\");\n\t\t}\n\t\treturn sum;\n\t}"
    }
  ],
  "3991": [
    {
      "state_id": 9,
      "candidate": "int",
      "candidate_text": "int"
    }
  ],
  "3995": [
    {
      "state_id": 775,
      "candidate": "identifier",
      "candidate_text": "sum"
    }
  ],
  "3999": [
    {
      "state_id": 1058,
      "candidate": "= expression",
      "candidate_text": "= 0"
    }
  ],
  "4001": [
    {
      "state_id": 146,
      "candidate": "decimal_integer_literal",
      "candidate_text": "0"
    }
  ],
  "4002": [
    {
      "state_id": 1369,
      "candidate": ";",
      "candidate_text": ";"
    }
  ],
  "4006": [
    {
      "state_id": 8,
      "candidate": "identifier",
      "candidate_text": "String"
    }
  ],
  "4013": [
    {
      "state_id": 775,
      "candidate": "identifier",
      "candidate_text": "num"
    }
  ],
  "4017": [
    {
      "state_id": 1058,
      "candidate": "= expression",
      "candidate_text": "= number + \"\""
    }
  ],
  "4019": [
    {
      "state_id": 146,
      "candidate": "identifier",
      "candidate_text": "number"
    }
  ],
  "4026": [
    {
      "state_id": 668,
      "candidate": "+ expression",
      "candidate_text": "+ \"\""
    }
  ],
  "4028": [
    {
      "state_id": 234,
      "candidate": "\" \"",
      "candidate_text": "\"\""
    }
  ],
  "4029": [
    {
      "state_id": 978,
      "candidate": "\"",
      "candidate_text": "\""
    }
  ],
  "4030": [
    {
      "state_id": 1369,
      "candidate": ";",
      "candidate_text": ";"
    }
  ],
  "4034": [
    {
      "state_id": 8,
      "candidate": "for ( local_variable_declaration expression ; expression ) statement",
      "candidate_text": "for (int i = getSize(number) - 1; i >= 0; i -= 2) {"
    }
  ],
  "4038": [
    {
      "state_id": 1376,
      "candidate": "( local_variable_declaration expression ; expression ) statement",
      "candidate_text": "(int i = getSize(number) - 1; i >= 0; i -= 2) {"
    }
  ],
  "4039": [
    {
      "state_id": 120,
      "candidate": "int",
      "candidate_text": "int"
    }
  ],
  "4043": [
    {
      "state_id": 780,
      "candidate": "identifier",
      "candidate_text": "i"
    }
  ],
  "4045": [
    {
      "state_id": 1066,
      "candidate": "= expression",
      "candidate_text": "= getSize(number) - 1"
    }
  ],
  "4047": [
    {
      "state_id": 146,
      "candidate": "identifier argument_list",
      "candidate_text": "getSize(number)"
    }
  ],
  "4054": [
    {
      "state_id": 413,
      "candidate": "( expression )",
      "candidate_text": "(number)"
    }
  ],
  "4055": [
    {
      "state_id": 155,
      "candidate": "identifier",
      "candidate_text": "number"
    }
  ],
  "4061": [
    {
      "state_id": 662,
      "candidate": ")",
      "candidate_text": ")"
    }
  ],
  "4063": [
    {
      "state_id": 668,
      "candidate": "- expression",
      "candidate_text": "- 1"
    }
  ],
  "4065": [
    {
      "state_id": 234,
      "candidate": "decimal_integer_literal",
      "candidate_text": "1"
    }
  ],
  "4066": [
    {
      "state_id": 1368,
      "candidate": ";",
      "candidate_text": ";"
    }
  ],
  "4068": [
    {
      "state_id": 182,
      "candidate": "identifier",
      "candidate_text": "i"
    }
  ],
  "4070": [
    {
      "state_id": 750,
      "candidate": ">= expression",
      "candidate_text": ">= 0"
    }
  ],
  "4073": [
    {
      "state_id": 230,
      "candidate": "decimal_integer_literal",
      "candidate_text": "0"
    }
  ],
  "4074": [
    {
      "state_id": 750,
      "candidate": "; expression ) statement",
      "candidate_text": "; i -= 2) {"
    }
  ],
  "4076": [
    {
      "state_id": 169,
      "candidate": "identifier -= expression",
      "candidate_text": "i -= 2"
    }
  ],
  "4078": [
    {
      "state_id": 413,
      "candidate": "-= expression",
      "candidate_text": "-= 2"
    }
  ],
  "4081": [
    {
      "state_id": 228,
      "candidate": "decimal_integer_literal",
      "candidate_text": "2"
    }
  ],
  "4082": [
    {
      "state_id": 678,
      "candidate": ") statement",
      "candidate_text": ") {"
    }
  ],
  "4084": [
    {
      "state_id": 63,
      "candidate": "{ statement }",
      "candidate_text": "{\n\t\t\tsum += Integer.parseInt(num.charAt(i) + \"\");\n\t\t}"
    }
  ],
  "4089": [
    {
      "state_id": 9,
      "candidate": "identifier += expression",
      "candidate_text": "sum += Integer.parseInt(num.charAt(i) + \"\")"
    }
  ],
  "4093": [
    {
      "state_id": 421,
      "candidate": "+= expression",
      "candidate_text": "+= Integer.parseInt(num.charAt(i) + \"\")"
    }
  ],
  "4096": [
    {
      "state_id": 228,
      "candidate": "identifier",
      "candidate_text": "Integer"
    }
  ],
  "4103": [
    {
      "state_id": 549,
      "candidate": ". identifier argument_list",
      "candidate_text": ".parseInt(num.charAt(i) + \"\")"
    }
  ],
  "4104": [
    {
      "state_id": 811,
      "candidate": "identifier argument_list",
      "candidate_text": "parseInt(num.charAt(i) + \"\")"
    }
  ],
  "4112": [
    {
      "state_id": 429,
      "candidate": "( expression )",
      "candidate_text": "(num.charAt(i) + \"\")"
    }
  ],
  "4113": [
    {
      "state_id": 155,
      "candidate": "identifier",
      "candidate_text": "num"
    }
  ],
  "4116": [
    {
      "state_id": 549,
      "candidate": ". identifier argument_list",
      "candidate_text": ".charAt(i)"
    }
  ],
  "4117": [
    {
      "state_id": 811,
      "candidate": "identifier argument_list",
      "candidate_text": "charAt(i)"
    }
  ],
  "4123": [
    {
      "state_id": 429,
      "candidate": "( expression )",
      "candidate_text": "(i)"
    }
  ],
  "4124": [
    {
      "state_id": 155,
      "candidate": "identifier",
      "candidate_text": "i"
    }
  ],
  "4125": [
    {
      "state_id": 662,
      "candidate": ")",
      "candidate_text": ")"
    }
  ],
  "4127": [
    {
      "state_id": 662,
      "candidate": "+ expression",
      "candidate_text": "+ \"\""
    }
  ],
  "4129": [
    {
      "state_id": 234,
      "candidate": "\" \"",
      "candidate_text": "\"\""
    }
  ],
  "4130": [
    {
      "state_id": 978,
      "candidate": "\"",
      "candidate_text": "\""
    }
  ],
  "4131": [
    {
      "state_id": 662,
      "candidate": ")",
      "candidate_text": ")"
    }
  ],
  "4132": [
    {
      "state_id": 752,
      "candidate": ";",
      "candidate_text": ";"
    }
  ],
  "4136": [
    {
      "state_id": 8,
      "candidate": "}",
      "candidate_text": "}"
    }
  ],
  "4140": [
    {
      "state_id": 8,
      "candidate": "return expression ;",
      "candidate_text": "return sum;"
    }
  ],
  "4147": [
    {
      "state_id": 149,
      "candidate": "identifier",
      "candidate_text": "sum"
    }
  ],
  "4150": [
    {
      "state_id": 729,
      "candidate": ";",
      "candidate_text": ";"
    }
  ],
  "4153": [
    {
      "state_id": 8,
      "candidate": "}",
      "candidate_text": "}"
    }
  ],
  "4156": [
    {
      "state_id": 412,
      "candidate": "enum_body_declarations_repeat1",
      "candidate_text": ""
    }
  ],
  "4216": [
    {
      "state_id": 410,
      "candidate": "public static",
      "candidate_text": "public static"
    }
  ],
  "4223": [
    {
      "state_id": 505,
      "candidate": "static",
      "candidate_text": "static"
    }
  ],
  "4230": [
    {
      "state_id": 698,
      "candidate": "boolean_type",
      "candidate_text": "boolean"
    }
  ],
  "4238": [
    {
      "state_id": 784,
      "candidate": "identifier formal_parameters",
      "candidate_text": "prefixMatched(long number, int d)"
    }
  ],
  "4251": [
    {
      "state_id": 867,
      "candidate": "( formal_parameter formal_parameters_repeat1 )",
      "candidate_text": "(long number, int d)"
    }
  ],
  "4252": [
    {
      "state_id": 471,
      "candidate": "long",
      "candidate_text": "long"
    }
  ],
  "4257": [
    {
      "state_id": 782,
      "candidate": "identifier",
      "candidate_text": "number"
    }
  ],
  "4263": [
    {
      "state_id": 1076,
      "candidate": ", formal_parameter",
      "candidate_text": ", int d"
    }
  ],
  "4265": [
    {
      "state_id": 483,
      "candidate": "int",
      "candidate_text": "int"
    }
  ],
  "4269": [
    {
      "state_id": 809,
      "candidate": "identifier",
      "candidate_text": "d"
    }
  ],
  "4270": [
    {
      "state_id": 1115,
      "candidate": ")",
      "candidate_text": ")"
    }
  ],
  "4272": [
    {
      "state_id": 1117,
      "candidate": "{ statement }",
      "candidate_text": "{\n\t\treturn getPrefix(number, getSize(d)) == d;\n\t}"
    }
  ],
  "4276": [
    {
      "state_id": 9,
      "candidate": "return expression ;",
      "candidate_text": "return getPrefix(number, getSize(d)) == d;"
    }
  ],
  "4283": [
    {
      "state_id": 149,
      "candidate": "identifier argument_list",
      "candidate_text": "getPrefix(number, getSize(d))"
    }
  ],
  "4292": [
    {
      "state_id": 413,
      "candidate": "( expression argument_list_repeat1 )",
      "candidate_text": "(number, getSize(d))"
    }
  ],
  "4293": [
    {
      "state_id": 155,
      "candidate": "identifier",
      "candidate_text": "number"
    }
  ],
  "4299": [
    {
      "state_id": 662,
      "candidate": ", expression",
      "candidate_text": ", getSize(d)"
    }
  ],
  "4301": [
    {
      "state_id": 199,
      "candidate": "identifier argument_list",
      "candidate_text": "getSize(d)"
    }
  ],
  "4308": [
    {
      "state_id": 413,
      "candidate": "( expression )",
      "candidate_text": "(d)"
    }
  ],
  "4309": [
    {
      "state_id": 155,
      "candidate": "identifier",
      "candidate_text": "d"
    }
  ],
  "4310": [
    {
      "state_id": 662,
      "candidate": ")",
      "candidate_text": ")"
    }
  ],
  "4311": [
    {
      "state_id": 1169,
      "candidate": ")",
      "candidate_text": ")"
    }
  ],
  "4313": [
    {
      "state_id": 729,
      "candidate": "== expression",
      "candidate_text": "== d"
    }
  ],
  "4316": [
    {
      "state_id": 231,
      "candidate": "identifier",
      "candidate_text": "d"
    }
  ],
  "4317": [
    {
      "state_id": 729,
      "candidate": ";",
      "candidate_text": ";"
    }
  ],
  "4320": [
    {
      "state_id": 8,
      "candidate": "}",
      "candidate_text": "}"
    }
  ],
  "4323": [
    {
      "state_id": 412,
      "candidate": "method_declaration",
      "candidate_text": ""
    }
  ],
  "4366": [
    {
      "state_id": 410,
      "candidate": "public static",
      "candidate_text": "public static"
    }
  ],
  "4373": [
    {
      "state_id": 505,
      "candidate": "static",
      "candidate_text": "static"
    }
  ],
  "4380": [
    {
      "state_id": 698,
      "candidate": "int",
      "candidate_text": "int"
    }
  ],
  "4384": [
    {
      "state_id": 784,
      "candidate": "identifier formal_parameters",
      "candidate_text": "getSize(long d)"
    }
  ],
  "4391": [
    {
      "state_id": 867,
      "candidate": "( formal_parameter )",
      "candidate_text": "(long d)"
    }
  ],
  "4392": [
    {
      "state_id": 471,
      "candidate": "long",
      "candidate_text": "long"
    }
  ],
  "4397": [
    {
      "state_id": 782,
      "candidate": "identifier",
      "candidate_text": "d"
    }
  ],
  "4398": [
    {
      "state_id": 1076,
      "candidate": ")",
      "candidate_text": ")"
    }
  ],
  "4400": [
    {
      "state_id": 1117,
      "candidate": "{ switch_block_statement_group_repeat2 }",
      "candidate_text": "{\n\t\tString num = d + \"\";\n\t\treturn num.length();\n\t}"
    }
  ],
  "4404": [
    {
      "state_id": 9,
      "candidate": "identifier",
      "candidate_text": "String"
    }
  ],
  "4411": [
    {
      "state_id": 775,
      "candidate": "identifier",
      "candidate_text": "num"
    }
  ],
  "4415": [
    {
      "state_id": 1058,
      "candidate": "= expression",
      "candidate_text": "= d + \"\""
    }
  ],
  "4417": [
    {
      "state_id": 146,
      "candidate": "identifier",
      "candidate_text": "d"
    }
  ],
  "4419": [
    {
      "state_id": 668,
      "candidate": "+ expression",
      "candidate_text": "+ \"\""
    }
  ],
  "4421": [
    {
      "state_id": 234,
      "candidate": "\" \"",
      "candidate_text": "\"\""
    }
  ],
  "4422": [
    {
      "state_id": 978,
      "candidate": "\"",
      "candidate_text": "\""
    }
  ],
  "4423": [
    {
      "state_id": 1369,
      "candidate": ";",
      "candidate_text": ";"
    }
  ],
  "4427": [
    {
      "state_id": 8,
      "candidate": "return expression ;",
      "candidate_text": "return num.length();"
    }
  ],
  "4434": [
    {
      "state_id": 149,
      "candidate": "identifier",
      "candidate_text": "num"
    }
  ],
  "4437": [
    {
      "state_id": 549,
      "candidate": ". identifier argument_list",
      "candidate_text": ".length()"
    }
  ],
  "4438": [
    {
      "state_id": 811,
      "candidate": "identifier argument_list",
      "candidate_text": "length()"
    }
  ],
  "4444": [
    {
      "state_id": 429,
      "candidate": "( )",
      "candidate_text": "()"
    }
  ],
  "4445": [
    {
      "state_id": 155,
      "candidate": ")",
      "candidate_text": ")"
    }
  ],
  "4446": [
    {
      "state_id": 729,
      "candidate": ";",
      "candidate_text": ";"
    }
  ],
  "4449": [
    {
      "state_id": 8,
      "candidate": "}",
      "candidate_text": "}"
    }
  ],
  "4452": [
    {
      "state_id": 410,
      "candidate": "method_declaration",
      "candidate_text": ""
    }
  ],
  "4579": [
    {
      "state_id": 410,
      "candidate": "public static",
      "candidate_text": "public static"
    }
  ],
  "4586": [
    {
      "state_id": 505,
      "candidate": "static",
      "candidate_text": "static"
    }
  ],
  "4593": [
    {
      "state_id": 698,
      "candidate": "long",
      "candidate_text": "long"
    }
  ],
  "4598": [
    {
      "state_id": 784,
      "candidate": "identifier formal_parameters",
      "candidate_text": "getPrefix(long number, int k)"
    }
  ],
  "4607": [
    {
      "state_id": 867,
      "candidate": "( formal_parameter formal_parameters_repeat1 )",
      "candidate_text": "(long number, int k)"
    }
  ],
  "4608": [
    {
      "state_id": 471,
      "candidate": "long",
      "candidate_text": "long"
    }
  ],
  "4613": [
    {
      "state_id": 782,
      "candidate": "identifier",
      "candidate_text": "number"
    }
  ],
  "4619": [
    {
      "state_id": 1076,
      "candidate": ", formal_parameter",
      "candidate_text": ", int k"
    }
  ],
  "4621": [
    {
      "state_id": 483,
      "candidate": "int",
      "candidate_text": "int"
    }
  ],
  "4625": [
    {
      "state_id": 809,
      "candidate": "identifier",
      "candidate_text": "k"
    }
  ],
  "4626": [
    {
      "state_id": 1115,
      "candidate": ")",
      "candidate_text": ")"
    }
  ],
  "4628": [
    {
      "state_id": 1117,
      "candidate": "{ switch_block_statement_group_repeat2 }",
      "candidate_text": "{\n\t\tif (getSize(number) > k)  {\n\t\t\tString num = number + \"\";\n\t\t\treturn  Long.parseLong(num.substring(0, k));\n\t\t}\n\t\treturn number;\n\t}"
    }
  ],
  "4632": [
    {
      "state_id": 9,
      "candidate": "if parenthesized_expression statement",
      "candidate_text": "if (getSize(number) > k)  {"
    }
  ],
  "4635": [
    {
      "state_id": 1236,
      "candidate": "( expression )",
      "candidate_text": "(getSize(number) > k)"
    }
  ],
  "4636": [
    {
      "state_id": 227,
      "candidate": "identifier argument_list",
      "candidate_text": "getSize(number)"
    }
  ],
  "4643": [
    {
      "state_id": 413,
      "candidate": "( expression )",
      "candidate_text": "(number)"
    }
  ],
  "4644": [
    {
      "state_id": 155,
      "candidate": "identifier",
      "candidate_text": "number"
    }
  ],
  "4650": [
    {
      "state_id": 662,
      "candidate": ")",
      "candidate_text": ")"
    }
  ],
  "4652": [
    {
      "state_id": 757,
      "candidate": "> expression",
      "candidate_text": "> k"
    }
  ],
  "4654": [
    {
      "state_id": 230,
      "candidate": "identifier",
      "candidate_text": "k"
    }
  ],
  "4655": [
    {
      "state_id": 757,
      "candidate": ")",
      "candidate_text": ")"
    }
  ],
  "4658": [
    {
      "state_id": 48,
      "candidate": "{ switch_block_statement_group_repeat2 }",
      "candidate_text": "{\n\t\t\tString num = number + \"\";\n\t\t\treturn  Long.parseLong(num.substring(0, k));\n\t\t}"
    }
  ],
  "4663": [
    {
      "state_id": 9,
      "candidate": "identifier",
      "candidate_text": "String"
    }
  ],
  "4670": [
    {
      "state_id": 775,
      "candidate": "identifier",
      "candidate_text": "num"
    }
  ],
  "4674": [
    {
      "state_id": 1058,
      "candidate": "= expression",
      "candidate_text": "= number + \"\""
    }
  ],
  "4676": [
    {
      "state_id": 146,
      "candidate": "identifier",
      "candidate_text": "number"
    }
  ],
  "4683": [
    {
      "state_id": 668,
      "candidate": "+ expression",
      "candidate_text": "+ \"\""
    }
  ],
  "4685": [
    {
      "state_id": 234,
      "candidate": "\" \"",
      "candidate_text": "\"\""
    }
  ],
  "4686": [
    {
      "state_id": 978,
      "candidate": "\"",
      "candidate_text": "\""
    }
  ],
  "4687": [
    {
      "state_id": 1369,
      "candidate": ";",
      "candidate_text": ";"
    }
  ],
  "4692": [
    {
      "state_id": 8,
      "candidate": "return expression ;",
      "candidate_text": "return  Long.parseLong(num.substring(0, k));"
    }
  ],
  "4700": [
    {
      "state_id": 149,
      "candidate": "identifier",
      "candidate_text": "Long"
    }
  ],
  "4704": [
    {
      "state_id": 549,
      "candidate": ". identifier argument_list",
      "candidate_text": ".parseLong(num.substring(0, k))"
    }
  ],
  "4705": [
    {
      "state_id": 811,
      "candidate": "identifier argument_list",
      "candidate_text": "parseLong(num.substring(0, k))"
    }
  ],
  "4714": [
    {
      "state_id": 429,
      "candidate": "( expression )",
      "candidate_text": "(num.substring(0, k))"
    }
  ],
  "4715": [
    {
      "state_id": 155,
      "candidate": "identifier",
      "candidate_text": "num"
    }
  ],
  "4718": [
    {
      "state_id": 549,
      "candidate": ". identifier argument_list",
      "candidate_text": ".substring(0, k)"
    }
  ],
  "4719": [
    {
      "state_id": 811,
      "candidate": "identifier argument_list",
      "candidate_text": "substring(0, k)"
    }
  ],
  "4728": [
    {
      "state_id": 429,
      "candidate": "( expression argument_list_repeat1 )",
      "candidate_text": "(0, k)"
    }
  ],
  "4729": [
    {
      "state_id": 155,
      "candidate": "decimal_integer_literal",
      "candidate_text": "0"
    }
  ],
  "4730": [
    {
      "state_id": 662,
      "candidate": ", expression",
      "candidate_text": ", k"
    }
  ],
  "4732": [
    {
      "state_id": 199,
      "candidate": "identifier",
      "candidate_text": "k"
    }
  ],
  "4733": [
    {
      "state_id": 1169,
      "candidate": ")",
      "candidate_text": ")"
    }
  ],
  "4734": [
    {
      "state_id": 662,
      "candidate": ")",
      "candidate_text": ")"
    }
  ],
  "4735": [
    {
      "state_id": 729,
      "candidate": ";",
      "candidate_text": ";"
    }
  ],
  "4739": [
    {
      "state_id": 8,
      "candidate": "}",
      "candidate_text": "}"
    }
  ],
  "4743": [
    {
      "state_id": 8,
      "candidate": "return expression ;",
      "candidate_text": "return number;"
    }
  ],
  "4750": [
    {
      "state_id": 149,
      "candidate": "identifier",
      "candidate_text": "number"
    }
  ],
  "4756": [
    {
      "state_id": 729,
      "candidate": ";",
      "candidate_text": ";"
    }
  ],
  "4759": [
    {
      "state_id": 8,
      "candidate": "}",
      "candidate_text": "}"
    }
  ],
  "4761": [
    {
      "state_id": 410,
      "candidate": "}",
      "candidate_text": "}"
    }
  ]
}